alumathpeergroup14/__init__.py
alumathpeergroup14/main.py
alumathgroup14-1.0.0.dist-info/LICENSE
alumathgroup14-1.0.0.dist-info/METADATA
alumathgroup14-1.0.0.dist-info/WHEEL
alumathgroup14-1.0.0.dist-info/top_level.txt
alumathgroup14-1.0.0.dist-info/RECORD
